Metadata-Version: 1.1
Name: mymymy
Version: 0.0.1
Summary: my test
Home-page: UNKNOWN
Author: ZD
Author-email: 995084571@qq.com
License: MIT
Platform: UNKNOWN
Classifier: Development Status :: 4 - Beta
Classifier: Intended Audience :: Developers
Classifier: Topic :: System :: Logging
Classifier: License :: OSI Approved :: MIT License
Classifier: Programming Language :: Python :: 3
